aiolifxc/CHANGES.txt
aiolifxc/__init__.py
aiolifxc/__main__.py
aiolifxc/aiolifx.py
aiolifxc/colors.py
aiolifxc/message.py
aiolifxc/msgtypes.py
aiolifxc/products.py
aiolifxc/unpack.py
aiolifxc/tests/__init__.py
aiolifxc/tests/test_lifx.py
aiolifxc-1.0.0.dist-info/DESCRIPTION.rst
aiolifxc-1.0.0.dist-info/METADATA
aiolifxc-1.0.0.dist-info/RECORD
aiolifxc-1.0.0.dist-info/WHEEL
aiolifxc-1.0.0.dist-info/metadata.json
aiolifxc-1.0.0.dist-info/top_level.txt
