Metadata-Version: 2.0
Name: aiolifxc
Version: 1.0.0
Summary: API for local communication with LIFX devices over a LAN with asyncio.
Home-page: http://github.com/brianmay/aiolifx
Author: Brian May
Author-email: brian@linuxpenguins.xyz
License: MIT
Keywords: lifx,light,automation
Platform: UNKNOWN
Classifier: Development Status :: 4 - Beta
Classifier: Intended Audience :: Developers
Classifier: License :: OSI Approved :: MIT License
Classifier: Natural Language :: English
Classifier: Programming Language :: Python :: 3.5
Classifier: Programming Language :: Python :: 3.6
Requires-Dist: bitstring
